zebranoise-0.1.1.dist-info/METADATA
zebranoise-0.1.1.dist-info/RECORD
zebranoise-0.1.1.dist-info/top_level.txt
zebranoise-0.1.1.dist-info/WHEEL
zebranoise-0.1.1.dist-info/licenses/LICENSE.txt
zebranoise/__init__.py
zebranoise/_perlin.cpython-39-x86_64-linux-gnu.so
zebranoise/perlin_stimulus.py
zebranoise/_version.py
zebranoise/easy.py
zebranoise/util.py
