Metadata-Version: 2.4
Name: zebranoise
Version: 0.1.1
Summary: Zebra noise stimuli for Python
Home-page: https://github.com/mwshinn/zebra_noise
Author: Max Shinn
Author-email: m.shinn@ucl.ac.uk
Classifier: Development Status :: 4 - Beta
Classifier: Programming Language :: C
Classifier: Programming Language :: Python :: 3
Classifier: Intended Audience :: Science/Research
Classifier: License :: OSI Approved :: MIT License
Classifier: Topic :: Multimedia :: Graphics
Classifier: Topic :: Scientific/Engineering
License-File: LICENSE.txt
Requires-Dist: numpy
Requires-Dist: imageio
Requires-Dist: imageio-ffmpeg
Requires-Dist: tqdm
Dynamic: author
Dynamic: author-email
Dynamic: classifier
Dynamic: description
Dynamic: description-content-type
Dynamic: home-page
Dynamic: license-file
Dynamic: requires-dist
Dynamic: summary
